{
	"backtrace" : 3,
	"backtraceGraph" : 
	{
		"commands" : 
		[
			"add_custom_target",
			"include"
		],
		"files" : 
		[
			"tools/test/misc/CMakeTestsRepart.cmake",
			"tools/test/misc/CMakeLists.txt"
		],
		"nodes" : 
		[
			{
				"file" : 1
			},
			{
				"command" : 1,
				"file" : 1,
				"line" : 59,
				"parent" : 0
			},
			{
				"file" : 0,
				"parent" : 1
			},
			{
				"command" : 0,
				"file" : 0,
				"line" : 46,
				"parent" : 2
			}
		]
	},
	"id" : "h5repart_files::@4e084b23b579099a9d2a",
	"name" : "h5repart_files",
	"paths" : 
	{
		"build" : "tools/test/misc",
		"source" : "tools/test/misc"
	},
	"sourceGroups" : 
	[
		{
			"name" : "",
			"sourceIndexes" : 
			[
				0
			]
		},
		{
			"name" : "CMake Rules",
			"sourceIndexes" : 
			[
				1,
				2,
				3,
				4,
				5,
				6,
				7,
				8,
				9,
				10,
				11,
				12,
				13,
				14,
				15,
				16,
				17,
				18,
				19
			]
		}
	],
	"sources" : 
	[
		{
			"backtrace" : 3,
			"isGenerated" : true,
			"path" : "out/build/x64-Debug/tools/test/misc/CMakeFiles/h5repart_files",
			"sourceGroupIndex" : 0
		},
		{
			"backtrace" : 0,
			"isGenerated" : true,
			"path" : "out/build/x64-Debug/tools/test/misc/CMakeFiles/h5repart_files.rule",
			"sourceGroupIndex" : 1
		},
		{
			"backtrace" : 0,
			"isGenerated" : true,
			"path" : "out/build/x64-Debug/tools/test/misc/family_file00000.h5.rule",
			"sourceGroupIndex" : 1
		},
		{
			"backtrace" : 0,
			"isGenerated" : true,
			"path" : "out/build/x64-Debug/tools/test/misc/family_file00001.h5.rule",
			"sourceGroupIndex" : 1
		},
		{
			"backtrace" : 0,
			"isGenerated" : true,
			"path" : "out/build/x64-Debug/tools/test/misc/family_file00002.h5.rule",
			"sourceGroupIndex" : 1
		},
		{
			"backtrace" : 0,
			"isGenerated" : true,
			"path" : "out/build/x64-Debug/tools/test/misc/family_file00003.h5.rule",
			"sourceGroupIndex" : 1
		},
		{
			"backtrace" : 0,
			"isGenerated" : true,
			"path" : "out/build/x64-Debug/tools/test/misc/family_file00004.h5.rule",
			"sourceGroupIndex" : 1
		},
		{
			"backtrace" : 0,
			"isGenerated" : true,
			"path" : "out/build/x64-Debug/tools/test/misc/family_file00005.h5.rule",
			"sourceGroupIndex" : 1
		},
		{
			"backtrace" : 0,
			"isGenerated" : true,
			"path" : "out/build/x64-Debug/tools/test/misc/family_file00006.h5.rule",
			"sourceGroupIndex" : 1
		},
		{
			"backtrace" : 0,
			"isGenerated" : true,
			"path" : "out/build/x64-Debug/tools/test/misc/family_file00007.h5.rule",
			"sourceGroupIndex" : 1
		},
		{
			"backtrace" : 0,
			"isGenerated" : true,
			"path" : "out/build/x64-Debug/tools/test/misc/family_file00008.h5.rule",
			"sourceGroupIndex" : 1
		},
		{
			"backtrace" : 0,
			"isGenerated" : true,
			"path" : "out/build/x64-Debug/tools/test/misc/family_file00009.h5.rule",
			"sourceGroupIndex" : 1
		},
		{
			"backtrace" : 0,
			"isGenerated" : true,
			"path" : "out/build/x64-Debug/tools/test/misc/family_file00010.h5.rule",
			"sourceGroupIndex" : 1
		},
		{
			"backtrace" : 0,
			"isGenerated" : true,
			"path" : "out/build/x64-Debug/tools/test/misc/family_file00011.h5.rule",
			"sourceGroupIndex" : 1
		},
		{
			"backtrace" : 0,
			"isGenerated" : true,
			"path" : "out/build/x64-Debug/tools/test/misc/family_file00012.h5.rule",
			"sourceGroupIndex" : 1
		},
		{
			"backtrace" : 0,
			"isGenerated" : true,
			"path" : "out/build/x64-Debug/tools/test/misc/family_file00013.h5.rule",
			"sourceGroupIndex" : 1
		},
		{
			"backtrace" : 0,
			"isGenerated" : true,
			"path" : "out/build/x64-Debug/tools/test/misc/family_file00014.h5.rule",
			"sourceGroupIndex" : 1
		},
		{
			"backtrace" : 0,
			"isGenerated" : true,
			"path" : "out/build/x64-Debug/tools/test/misc/family_file00015.h5.rule",
			"sourceGroupIndex" : 1
		},
		{
			"backtrace" : 0,
			"isGenerated" : true,
			"path" : "out/build/x64-Debug/tools/test/misc/family_file00016.h5.rule",
			"sourceGroupIndex" : 1
		},
		{
			"backtrace" : 0,
			"isGenerated" : true,
			"path" : "out/build/x64-Debug/tools/test/misc/family_file00017.h5.rule",
			"sourceGroupIndex" : 1
		}
	],
	"type" : "UTILITY"
}
